{
  "_class": "symbolInstance",
  "booleanOperation": -1,
  "do_objectID": "2D1B5FFD-3DDE-4955-A2CA-7DAD60E42578",
  "exportOptions": {
    "_class": "exportOptions",
    "do_objectID": "4938BEFB-95B7-4D50-92ED-44C1946BB854",
    "exportFormats": [
    ],
    "includedLayerIds": [
    ],
    "layerOptions": 0,
    "shouldTrim": false
  },
  "frame": {
    "_class": "rect",
    "constrainProportions": false,
    "do_objectID": "E3D3658A-98F3-4DDE-B8B0-1B2A795AFF05",
    "height": 125,
    "width": 353,
    "x": 11,
    "y": 0
  },
  "horizontalSpacing": 0,
  "isFixedToViewport": false,
  "isFlippedHorizontal": false,
  "isFlippedVertical": false,
  "isLocked": false,
  "isVisible": true,
  "layerListExpandedType": 0,
  "name": "molecule/head",
  "nameIsFixed": false,
  "overrideValues": [
  ],
  "resizingConstraint": 63,
  "resizingType": 0,
  "rotation": 0,
  "scale": 1,
  "shouldBreakMaskChain": false,
  "style": {
    "_class": "style",
    "do_objectID": "89E6CE13-D97B-4382-8427-EFE3E4E75385",
    "endMarkerType": 0,
    "miterLimit": 10,
    "startMarkerType": 0,
    "windingRule": 1
  },
  "symbolID": "F3BFA1D8-2F5C-4A01-A1A9-2B65017A66FD",
  "verticalSpacing": 0
}