{
  "_class": "artboard",
  "backgroundColor": {
    "_class": "color",
    "alpha": 1,
    "blue": 1,
    "do_objectID": "0873E2BD-7851-41DA-B8B9-5D5F7FC26A5B",
    "green": 1,
    "red": 1
  },
  "booleanOperation": -1,
  "do_objectID": "A03998D0-6405-40DB-8A60-F23E4658D7F3",
  "exportOptions": {
    "_class": "exportOptions",
    "do_objectID": "686C8416-01D4-4625-9B72-E5CB07B59646",
    "exportFormats": [
    ],
    "includedLayerIds": [
    ],
    "layerOptions": 0,
    "shouldTrim": false
  },
  "frame": {
    "_class": "rect",
    "constrainProportions": false,
    "do_objectID": "ABA316B0-366C-4015-A957-720ECB6AE5EF",
    "height": 667,
    "width": 375,
    "x": 638,
    "y": 1796
  },
  "hasBackgroundColor": true,
  "hasClickThrough": false,
  "horizontalRulerData": {
    "_class": "rulerData",
    "base": 0,
    "do_objectID": "BFA0FFAA-2F64-4F06-9965-8F9827982403",
    "guides": [
    ]
  },
  "includeBackgroundColorInExport": true,
  "includeInCloudUpload": true,
  "isFixedToViewport": false,
  "isFlippedHorizontal": false,
  "isFlippedVertical": false,
  "isFlowHome": false,
  "isLocked": false,
  "isVisible": true,
  "layerListExpandedType": 2,
  "layers": [
    {
      "class": "symbolInstance",
      "id": "1E585425-E843-4D7D-A02A-C5E0359B6B42"
    },
    {
      "class": "symbolInstance",
      "id": "503A896F-0B14-4E21-B5DE-E534982BE839"
    },
    {
      "class": "symbolInstance",
      "id": "7994BCA8-70F4-403D-8A6B-F293DB55F0CC"
    }
  ],
  "layout": {
    "_class": "layoutGrid",
    "columnWidth": 26.25,
    "do_objectID": "23C60FEF-E19C-49E4-BB09-EEF32ED2EF69",
    "drawHorizontal": false,
    "drawHorizontalLines": false,
    "drawVertical": true,
    "gutterHeight": 12,
    "gutterWidth": 3.333333333333333,
    "guttersOutside": true,
    "horizontalOffset": 10,
    "isEnabled": true,
    "numberOfColumns": 12,
    "rowHeightMultiplication": 5,
    "totalWidth": 355
  },
  "name": "Authentication",
  "nameIsFixed": true,
  "presetDictionary": {
    "allowResizedMatching": 1,
    "height": 667,
    "name": "iPhone 8",
    "offersLandscapeVariant": 1,
    "width": 375
  },
  "resizesContent": true,
  "resizingConstraint": 63,
  "resizingType": 0,
  "rotation": 0,
  "shouldBreakMaskChain": true,
  "style": {
    "_class": "style",
    "do_objectID": "1F8FBE34-5B2B-4AF2-98A7-362B8BCC148B",
    "endMarkerType": 0,
    "miterLimit": 10,
    "startMarkerType": 0,
    "windingRule": 1
  },
  "verticalRulerData": {
    "_class": "rulerData",
    "base": 0,
    "do_objectID": "CFF06F15-0885-4FBC-ABDE-F6F13817A879",
    "guides": [
    ]
  }
}